{"sitedata":[{"sitename":"Banning Lewis Ranch","icon":"/img/favicon.png","logo":"https://res.cloudinary.com/drjzrh756/image/upload/v1536440227/kavezxc3xc2k9fzabwrk.png","metadesc":"Trusted By Fine Real Estate Professionals","metauthor":"Fly My Community","metakeyword":"cms"}],"content":[{"email":"erintaylor@kw.com","linkcont":"719-301-9421","videoid":"233413663","sliderbg":"/img/sliderbg.jpg"}],"about":[{"abouttext1":"Banning Lewis Ranch","abouttext2":"Banning Lewis Ranch is a premier master planned community in North Eastern Colorado Springs.","aboutbg":"/img/content_bg.png"}],"updatedDate":"2017-11-28T06:24:37.530Z"}